<?xml version="1.0" encoding="UTF-8"?><record_update table="sp_instance">
    <sp_instance action="INSERT_OR_UPDATE">
        <active>true</active>
        <class_name/>
        <color>default</color>
        <css/>
        <glyph/>
        <id/>
        <order>2</order>
        <roles/>
        <short_description/>
        <size>md</size>
        <sp_column display_value="2">6bd5a4bc07df1110cd89f4218c1ed086</sp_column>
        <sp_widget display_value="HTML">8679ef89cb21120000f8d856634c9c4f</sp_widget>
        <sys_class_name>sp_instance</sys_class_name>
        <sys_created_by>admin</sys_created_by>
        <sys_created_on>2022-11-18 16:17:23</sys_created_on>
        <sys_id>d60aa4b007135110cd89f4218c1ed050</sys_id>
        <sys_name/>
        <sys_package display_value="DREAM_BOOKING" source="x_938860_dream_boo">ed3ebf2b0747d110cd89f4218c1ed09d</sys_package>
        <sys_policy/>
        <sys_scope display_value="DREAM_BOOKING">ed3ebf2b0747d110cd89f4218c1ed09d</sys_scope>
        <sys_update_name>sp_instance_d60aa4b007135110cd89f4218c1ed050</sys_update_name>
        <title/>
        <url/>
        <widget_parameters><![CDATA[{
	"html": {
		"value": "<h1 id=\"black-friday-holiday-deals-2022\">Black Friday movie-themed holiday resorts deals 2022</h1>\r\n<p>It&rsquo;s time! Black Friday is officially here, and you can now book dreamy movie-themed holidays with irresistible discounts. For a limited time only, you can make savings of up to an extra 20% on selected hotels. In addition, many of our budget-friendly holidays have flexible payment options, including monthly instalments and low deposits from &pound;25 per person.</p>",
		"displayValue": "<h1 id=\"black-friday-holiday-deals-2022\">Black Friday movie-themed holiday resorts deals 2022</h1>\n<p>It&rsquo;s time! Black Friday is officially here, and you can now book dreamy movie-themed holidays with irresistible discounts. For a limited time only, you can make savings of up to an extra 20% on selected hotels. In addition, many of our budget-friendly holidays have flexible payment options, including monthly instalments and low deposits from &pound;25 per person.</p>"
	}
}]]></widget_parameters>
    </sp_instance>
    <sys_translated_text action="delete_multiple" query="documentkey=d60aa4b007135110cd89f4218c1ed050"/>
</record_update>
